check_mcp/__init__.py
check_mcp/__main__.py
check_mcp/config.py
check_mcp/cve.py
check_mcp/release.py
check_mcp/server.py
check_mcp-0.0.20.dist-info/METADATA
check_mcp-0.0.20.dist-info/WHEEL
check_mcp-0.0.20.dist-info/entry_points.txt
check_mcp-0.0.20.dist-info/RECORD
